{
  "uid":"A12",
  "title":"শ্রীরাধারাণীর আরতি",
  "author":"মনোহর দাস",
  "language":"ben",
  "notes":[],
  "audio":[],
  "has_synonyms":false,
  "has_translations":false,
  "legend":{"w":"word","h":"hint","s":"synonym","o":"override"},
  "verses":[{
    "lines":[
      [{"w":"জয়","h":" ","s":{"eng":"NULL"},"o":{}},{"w":"জয়","h":" ","s":{"eng":"NULL"},"o":{}},{"w":"রাধেজীকো","h":" ","s":{"eng":"NULL"},"o":{}},{"w":"শরণ","h":" ","s":{"eng":"NULL"},"o":{}},{"w":"তোঁহারি","h":" ।","s":{"eng":"NULL"},"o":{}}],
      [{"w":"ঐছন","h":" ","s":{"eng":"NULL"},"o":{}},{"w":"আরতি","h":" ","s":{"eng":"NULL"},"o":{}},{"w":"যাও","h":" ","s":{"eng":"NULL"},"o":{}},{"w":"বলিহারী","h":" ॥১॥","s":{"eng":"NULL"},"o":{}}]],
    "translation":{"eng":"UNDEFINED"}},{
    "lines":[
      [{"w":"পাট","h":" ","s":{"eng":"NULL"},"o":{}},{"w":"পটাম্বর","h":" ","s":{"eng":"NULL"},"o":{}},{"w":"উড়ে","h":" ","s":{"eng":"NULL"},"o":{}},{"w":"নীল","h":" ","s":{"eng":"NULL"},"o":{}},{"w":"শাড়ী","h":" ।","s":{"eng":"NULL"},"o":{}}],
      [{"w":"সিঁথিপর","h":" ","s":{"eng":"NULL"},"o":{}},{"w":"সিন্দুর","h":" ","s":{"eng":"NULL"},"o":{}},{"w":"যাই","h":" ","s":{"eng":"NULL"},"o":{}},{"w":"বলিহারী","h":" ॥২॥","s":{"eng":"NULL"},"o":{}}]],
    "translation":{"eng":"UNDEFINED"}},{
    "lines":[
      [{"w":"বেশ","h":" ","s":{"eng":"NULL"},"o":{}},{"w":"বনাওত","h":" ","s":{"eng":"NULL"},"o":{}},{"w":"প্রিয়","h":" ","s":{"eng":"NULL"},"o":{}},{"w":"সহচরী","h":" ।","s":{"eng":"NULL"},"o":{}}],
      [{"w":"রতন","h":" ","s":{"eng":"NULL"},"o":{}},{"w":"সিংহাসনে","h":" ","s":{"eng":"NULL"},"o":{}},{"w":"বৈঠল","h":" ","s":{"eng":"NULL"},"o":{}},{"w":"গৌরী","h":" ॥৩॥","s":{"eng":"NULL"},"o":{}}]],
    "translation":{"eng":"UNDEFINED"}},{
    "lines":[
      [{"w":"রতনে","h":" ","s":{"eng":"NULL"},"o":{}},{"w":"জড়িত","h":" ","s":{"eng":"NULL"},"o":{}},{"w":"মণি","h":" ","s":{"eng":"NULL"},"o":{}},{"w":"মাণিক","h":" ","s":{"eng":"NULL"},"o":{}},{"w":"মোতি","h":" ।","s":{"eng":"NULL"},"o":{}}],
      [{"w":"ঝলকত","h":" ","s":{"eng":"NULL"},"o":{}},{"w":"আভরণ","h":" ","s":{"eng":"NULL"},"o":{}},{"w":"প্রতি","h":" ","s":{"eng":"NULL"},"o":{}},{"w":"অঙ্গে","h":" ","s":{"eng":"NULL"},"o":{}},{"w":"জ্যোতি","h":" ॥৪॥","s":{"eng":"NULL"},"o":{}}]],
    "translation":{"eng":"UNDEFINED"}},{
    "lines":[
      [{"w":"চুয়া","h":" ","s":{"eng":"NULL"},"o":{}},{"w":"চন্দন","h":" ","s":{"eng":"NULL"},"o":{}},{"w":"অঙ্গে","h":" ","s":{"eng":"NULL"},"o":{}},{"w":"দেই","h":" ","s":{"eng":"NULL"},"o":{}},{"w":"ব্রজবালা","h":" ।","s":{"eng":"NULL"},"o":{}}],
      [{"w":"কত","h":" ","s":{"eng":"NULL"},"o":{}},{"w":"কোটী","h":" ","s":{"eng":"NULL"},"o":{}},{"w":"চন্দ্র","h":" ","s":{"eng":"NULL"},"o":{}},{"w":"জিনি","h":" ","s":{"eng":"NULL"},"o":{}},{"w":"বদন","h":" ","s":{"eng":"NULL"},"o":{}},{"w":"উজলা","h":" ॥৫॥","s":{"eng":"NULL"},"o":{}}]],
    "translation":{"eng":"UNDEFINED"}},{
    "lines":[
      [{"w":"চৌদিকে","h":" ","s":{"eng":"NULL"},"o":{}},{"w":"সখীগণ","h":" ","s":{"eng":"NULL"},"o":{}},{"w":"দেই","h":" ","s":{"eng":"NULL"},"o":{}},{"w":"করতালি","h":" ।","s":{"eng":"NULL"},"o":{}}],
      [{"w":"আরতি","h":" ","s":{"eng":"NULL"},"o":{}},{"w":"করতঁহি","h":" ","s":{"eng":"NULL"},"o":{}},{"w":"ললিতা","h":" ","s":{"eng":"NULL"},"o":{}},{"w":"পিয়ারী","h":" ॥৬॥","s":{"eng":"NULL"},"o":{}}]],
    "translation":{"eng":"UNDEFINED"}},{
    "lines":[
      [{"w":"নব","h":" ","s":{"eng":"NULL"},"o":{}},{"w":"নব","h":" ","s":{"eng":"NULL"},"o":{}},{"w":"ব্রজবধূ","h":" ","s":{"eng":"NULL"},"o":{}},{"w":"মঙ্গল","h":" ","s":{"eng":"NULL"},"o":{}},{"w":"গাওয়ে","h":" ।","s":{"eng":"NULL"},"o":{}}],
      [{"w":"প্রিয়","h":" ","s":{"eng":"NULL"},"o":{}},{"w":"নর্ম্মসখীগণ","h":" ","s":{"eng":"NULL"},"o":{}},{"w":"চামর","h":" ","s":{"eng":"NULL"},"o":{}},{"w":"ঢুলাওয়ে","h":" ॥৭॥","s":{"eng":"NULL"},"o":{}}]],
    "translation":{"eng":"UNDEFINED"}},{
    "lines":[
      [{"w":"রাধাপদ","h":"-","s":{"eng":"NULL"},"o":{}},{"w":"পঙ্কজ","h":" ","s":{"eng":"NULL"},"o":{}},{"w":"সেবনকি","h":" ","s":{"eng":"NULL"},"o":{}},{"w":"আশা","h":" ।","s":{"eng":"NULL"},"o":{}}],
      [{"w":"দাস","h":" ","s":{"eng":"NULL"},"o":{}},{"w":"মনোহর","h":" ","s":{"eng":"NULL"},"o":{}},{"w":"করত","h":" ","s":{"eng":"NULL"},"o":{}},{"w":"ভরসা","h":" ॥৮॥","s":{"eng":"NULL"},"o":{}}]],
    "translation":{"eng":"UNDEFINED"}}
  ]
}
