{
  "uid":"D21",
  "title":"आली! म्हांने लागे वृन्दावन नीको",
  "author":"मीराबाइ",
  "language":"hin",
  "notes":[],
  "audio":[
    {"uid":"krsn-1","fn":"D21-krsn-1.mp3","meta":{"artist":"Krsnadas das","src":"21 Hindi & Braj Bhasha Kīrtanas/[19] Ālī! Mohe Lāge Vṛndāvana Nīko/krsn-ali_mohe_lage_vrndavana_niko.mp3"}}],
  "has_synonyms":false,
  "has_translations":false,
  "legend":{"w":"word","h":"hint","s":"synonym","o":"override"},
  "verses":[{
    "lines":[
      [{"w":"आली","h":"! ","s":{"eng":"NULL"},"o":{}},{"w":"म्हांने","h":" ","s":{"eng":"NULL"},"o":{}},{"w":"लागे","h":" ","s":{"eng":"NULL"},"o":{}},{"w":"वृन्दावन","h":" ","s":{"eng":"NULL"},"o":{}},{"w":"नीको","h":",","s":{"eng":"NULL"},"o":{}}],
      [{"w":"घर","h":" ","s":{"eng":"NULL"},"o":{}},{"w":"घर","h":" ","s":{"eng":"NULL"},"o":{}},{"w":"तुलसी","h":", ","s":{"eng":"NULL"},"o":{}},{"w":"ठाकुर","h":" ","s":{"eng":"NULL"},"o":{}},{"w":"पूजा","h":", ","s":{"eng":"NULL"},"o":{}}],
      [{"w":"दर्शन","h":" ","s":{"eng":"NULL"},"o":{}},{"w":"गोविन्दजी","h":" ","s":{"eng":"NULL"},"o":{}},{"w":"को","h":" ॥","s":{"eng":"NULL"},"o":{}},{"w":"१","h":"॥","s":{"eng":"NULL"},"o":{}}]],
    "translation":{"eng":"UNDEFINED"}},{
    "lines":[
      [{"w":"निर्मल","h":" ","s":{"eng":"NULL"},"o":{}},{"w":"नीर","h":" ","s":{"eng":"NULL"},"o":{}},{"w":"बहत","h":" ","s":{"eng":"NULL"},"o":{}},{"w":"यमुना","h":" ","s":{"eng":"NULL"},"o":{}},{"w":"को","h":", ","s":{"eng":"NULL"},"o":{}}],
      [{"w":"भोजन","h":" ","s":{"eng":"NULL"},"o":{}},{"w":"दूध","h":" ","s":{"eng":"NULL"},"o":{}},{"w":"दही","h":" ","s":{"eng":"NULL"},"o":{}},{"w":"को","h":" ॥","s":{"eng":"NULL"},"o":{}},{"w":"२","h":"॥","s":{"eng":"NULL"},"o":{}}]],
    "translation":{"eng":"UNDEFINED"}},{
    "lines":[
      [{"w":"रत्न","h":" ","s":{"eng":"NULL"},"o":{}},{"w":"सिंहासन","h":" ","s":{"eng":"NULL"},"o":{}},{"w":"आप","h":" ","s":{"eng":"NULL"},"o":{}},{"w":"विराजे","h":", ","s":{"eng":"NULL"},"o":{}}],
      [{"w":"मुकुट","h":" ","s":{"eng":"NULL"},"o":{}},{"w":"धर्यो","h":" ","s":{"eng":"NULL"},"o":{}},{"w":"तुलसी","h":" ","s":{"eng":"NULL"},"o":{}},{"w":"को","h":" ॥","s":{"eng":"NULL"},"o":{}},{"w":"३","h":"॥","s":{"eng":"NULL"},"o":{}}]],
    "translation":{"eng":"UNDEFINED"}},{
    "lines":[
      [{"w":"कुञ्जन","h":" ","s":{"eng":"NULL"},"o":{}},{"w":"कुञ्जन","h":" ","s":{"eng":"NULL"},"o":{}},{"w":"रहत","h":" ","s":{"eng":"NULL"},"o":{}},{"w":"राधिका","h":", ","s":{"eng":"NULL"},"o":{}}],
      [{"w":"शब्द","h":" ","s":{"eng":"NULL"},"o":{}},{"w":"सुनत","h":" ","s":{"eng":"NULL"},"o":{}},{"w":"मुरली","h":" ","s":{"eng":"NULL"},"o":{}},{"w":"को","h":" ॥","s":{"eng":"NULL"},"o":{}},{"w":"४","h":"॥","s":{"eng":"NULL"},"o":{}}]],
    "translation":{"eng":"UNDEFINED"}},{
    "lines":[
      [{"w":"मीरा","h":" ","s":{"eng":"NULL"},"o":{}},{"w":"के","h":" ","s":{"eng":"NULL"},"o":{}},{"w":"प्रभु","h":" ","s":{"eng":"NULL"},"o":{}},{"w":"गिरिधरनागर","h":", ","s":{"eng":"NULL"},"o":{}}],
      [{"w":"भजन","h":" ","s":{"eng":"NULL"},"o":{}},{"w":"बिना","h":" ","s":{"eng":"NULL"},"o":{}},{"w":"नर","h":" ","s":{"eng":"NULL"},"o":{}},{"w":"फीको","h":" ॥","s":{"eng":"NULL"},"o":{}},{"w":"५","h":"॥","s":{"eng":"NULL"},"o":{}}]],
    "translation":{"eng":"UNDEFINED"}}
  ]
}