{
  "uid":"GG1",
  "title":"রতি-সুখ-সারে",
  "author":"শ্রীজয়দেৱ গোস্ৱামী",
  "language":"san",
  "notes":[],
  "audio":[
    {"uid":"tama-1","fn":"GG1-tama-1.mp3","meta":{"artist":"Tamal Krsna das","src":"20 Sanskrit Songs/[15] Rati-sukha-sāre/tama-rati_sukha_sare.mp3"}}],
  "has_synonyms":false,
  "has_translations":false,
  "legend":{"w":"word","h":"hint","s":"synonym","o":"override"},
  "verses":[{
    "lines":[
      [{"w":"রতি","h":"-","s":{"eng":"NULL"},"o":{}},{"w":"সুখ","h":"-","s":{"eng":"NULL"},"o":{}},{"w":"সারে","h":" ","s":{"eng":"NULL"},"o":{}},{"w":"গতমভিসারে","h":"","s":{"eng":"NULL"},"o":{}}],
      [{"w":"মদন","h":"-","s":{"eng":"NULL"},"o":{}},{"w":"মনোহরৱেষম্","h":" ।","s":{"eng":"NULL"},"o":{}}],
      [{"w":"ন","h":" ","s":{"eng":"NULL"},"o":{}},{"w":"কুরু","h":" ","s":{"eng":"NULL"},"o":{}},{"w":"নিতম্বিনি","h":"! ","s":{"eng":"NULL"},"o":{}},{"w":"গমন","h":"-","s":{"eng":"NULL"},"o":{}},{"w":"ৱিলম্বনম্","h":"","s":{"eng":"NULL"},"o":{}}],
      [{"w":"অনুসর","h":" ","s":{"eng":"NULL"},"o":{}},{"w":"তং","h":" ","s":{"eng":"NULL"},"o":{}},{"w":"হৃদয়েশম্","h":" ॥১॥","s":{"eng":"NULL"},"o":{}}]],
    "translation":{"eng":"UNDEFINED"}},{
    "lines":[
      [{"w":"ধীর","h":" ","s":{"eng":"NULL"},"o":{}},{"w":"সমীরে","h":" ","s":{"eng":"NULL"},"o":{}},{"w":"যমুনা","h":" ","s":{"eng":"NULL"},"o":{}},{"w":"তীরে","h":"","s":{"eng":"NULL"},"o":{}}],
      [{"w":"ৱসতি","h":" ","s":{"eng":"NULL"},"o":{}},{"w":"ৱনে","h":" ","s":{"eng":"NULL"},"o":{}},{"w":"ৱনমালী","h":" ।","s":{"eng":"NULL"},"o":{}}],
      [{"w":"পীনপয়োধরপরিসরমর্দন","h":"-","s":{"eng":"NULL"},"o":{}}],
      [{"w":"চঞ্চলকরয়ুগশালী","h":" ॥","s":{"eng":"NULL"},"o":{}},{"w":"ধ্রু","h":"॥","s":{"eng":"NULL"},"o":{}}]],
    "translation":{"eng":"UNDEFINED"}},{
    "lines":[
      [{"w":"নাম","h":"-","s":{"eng":"NULL"},"o":{}},{"w":"সমেতং","h":" ","s":{"eng":"NULL"},"o":{}},{"w":"কৃত","h":"-","s":{"eng":"NULL"},"o":{}},{"w":"সঙ্কেতং","h":"","s":{"eng":"NULL"},"o":{}}],
      [{"w":"ৱাদয়তে","h":" ","s":{"eng":"NULL"},"o":{}},{"w":"মৃদুৱেণুম্","h":" ।","s":{"eng":"NULL"},"o":{}}],
      [{"w":"বহু","h":" ","s":{"eng":"NULL"},"o":{}},{"w":"মনুতেঽঅনু","h":" ","s":{"eng":"NULL"},"o":{}},{"w":"তে","h":" ","s":{"eng":"NULL"},"o":{}},{"w":"তনু","h":"-","s":{"eng":"NULL"},"o":{}},{"w":"সঙ্গত","h":"-","s":{"eng":"NULL"},"o":{}}],
      [{"w":"পৱন","h":"-","s":{"eng":"NULL"},"o":{}},{"w":"চলিতমপি","h":" ","s":{"eng":"NULL"},"o":{}},{"w":"রেণুম্","h":" ॥২॥","s":{"eng":"NULL"},"o":{}}]],
    "translation":{"eng":"UNDEFINED"}},{
    "lines":[
      [{"w":"পততি","h":" ","s":{"eng":"NULL"},"o":{}},{"w":"পতত্রে","h":" ","s":{"eng":"NULL"},"o":{}},{"w":"ৱিচলতি","h":" ","s":{"eng":"NULL"},"o":{}},{"w":"পত্রে","h":"","s":{"eng":"NULL"},"o":{}}],
      [{"w":"শঙ্কিত","h":"-","s":{"eng":"NULL"},"o":{}},{"w":"ভৱদুপয়ানম্","h":" ।","s":{"eng":"NULL"},"o":{}}],
      [{"w":"রচয়তি","h":" ","s":{"eng":"NULL"},"o":{}},{"w":"শয়নং","h":" ","s":{"eng":"NULL"},"o":{}},{"w":"সচকিত","h":"-","s":{"eng":"NULL"},"o":{}},{"w":"নয়নং","h":"","s":{"eng":"NULL"},"o":{}}],
      [{"w":"পশ্যতি","h":" ","s":{"eng":"NULL"},"o":{}},{"w":"তৱ","h":" ","s":{"eng":"NULL"},"o":{}},{"w":"পন্থানম্","h":" ॥৩॥","s":{"eng":"NULL"},"o":{}}]],
    "translation":{"eng":"UNDEFINED"}},{
    "lines":[
      [{"w":"মুখরমধীরং","h":" ","s":{"eng":"NULL"},"o":{}},{"w":"ত্যজ","h":" ","s":{"eng":"NULL"},"o":{}},{"w":"মঞ্জীরং","h":"","s":{"eng":"NULL"},"o":{}}],
      [{"w":"রিপুমিৱ","h":" ","s":{"eng":"NULL"},"o":{}},{"w":"কেলিষু","h":" ","s":{"eng":"NULL"},"o":{}},{"w":"লোলম্","h":" ।","s":{"eng":"NULL"},"o":{}}],
      [{"w":"চল","h":" ","s":{"eng":"NULL"},"o":{}},{"w":"সখি","h":"! ","s":{"eng":"NULL"},"o":{}},{"w":"কুঞ্জং","h":" ","s":{"eng":"NULL"},"o":{}},{"w":"সতিমির","h":"-","s":{"eng":"NULL"},"o":{}},{"w":"পুঞ্জং","h":"","s":{"eng":"NULL"},"o":{}}],
      [{"w":"শীলয়","h":" ","s":{"eng":"NULL"},"o":{}},{"w":"নীল","h":"-","s":{"eng":"NULL"},"o":{}},{"w":"নিচোলম্","h":" ॥৪॥","s":{"eng":"NULL"},"o":{}}]],
    "translation":{"eng":"UNDEFINED"}},{
    "lines":[
      [{"w":"উরসি","h":" ","s":{"eng":"NULL"},"o":{}},{"w":"মুরারেরুপহিত","h":"-","s":{"eng":"NULL"},"o":{}},{"w":"হারে","h":"","s":{"eng":"NULL"},"o":{}}],
      [{"w":"ঘন","h":" ","s":{"eng":"NULL"},"o":{}},{"w":"ইৱ","h":" ","s":{"eng":"NULL"},"o":{}},{"w":"তরল","h":"-","s":{"eng":"NULL"},"o":{}},{"w":"বলাকে","h":" ।","s":{"eng":"NULL"},"o":{}}],
      [{"w":"তডিদিৱ","h":" ","s":{"eng":"NULL"},"o":{}},{"w":"পীতে","h":"! ","s":{"eng":"NULL"},"o":{}},{"w":"রতি","h":"-","s":{"eng":"NULL"},"o":{}},{"w":"ৱিপরীতে","h":"","s":{"eng":"NULL"},"o":{}}],
      [{"w":"রাজসি","h":" ","s":{"eng":"NULL"},"o":{}},{"w":"সুকৃত","h":"-","s":{"eng":"NULL"},"o":{}},{"w":"ৱিপাকে","h":" ॥৫॥","s":{"eng":"NULL"},"o":{}}]],
    "translation":{"eng":"UNDEFINED"}},{
    "lines":[
      [{"w":"ৱিগলিত","h":"-","s":{"eng":"NULL"},"o":{}},{"w":"ৱসনং","h":" ","s":{"eng":"NULL"},"o":{}},{"w":"পরিহৃত","h":"-","s":{"eng":"NULL"},"o":{}},{"w":"রসনং","h":"","s":{"eng":"NULL"},"o":{}}],
      [{"w":"ঘটয়","h":" ","s":{"eng":"NULL"},"o":{}},{"w":"জঘনমপিধানম্","h":" ।","s":{"eng":"NULL"},"o":{}}],
      [{"w":"কিসলয়","h":"-","s":{"eng":"NULL"},"o":{}},{"w":"শয়নে","h":" ","s":{"eng":"NULL"},"o":{}},{"w":"পঙ্কজ","h":"-","s":{"eng":"NULL"},"o":{}},{"w":"নয়নে","h":"","s":{"eng":"NULL"},"o":{}}],
      [{"w":"নিধিমিৱ","h":" ","s":{"eng":"NULL"},"o":{}},{"w":"হর্ষ","h":"-","s":{"eng":"NULL"},"o":{}},{"w":"নিধানম্","h":" ॥৬॥","s":{"eng":"NULL"},"o":{}}]],
    "translation":{"eng":"UNDEFINED"}},{
    "lines":[
      [{"w":"হরিরভিমানী","h":" ","s":{"eng":"NULL"},"o":{}},{"w":"রজনিরিদানীম্","h":"","s":{"eng":"NULL"},"o":{}}],
      [{"w":"ইয়ম্","h":" ","s":{"eng":"NULL"},"o":{}},{"w":"অপি","h":" ","s":{"eng":"NULL"},"o":{}},{"w":"যাতি","h":" ","s":{"eng":"NULL"},"o":{}},{"w":"ৱিরামম্","h":" ।","s":{"eng":"NULL"},"o":{}}],
      [{"w":"কুরু","h":" ","s":{"eng":"NULL"},"o":{}},{"w":"মম","h":" ","s":{"eng":"NULL"},"o":{}},{"w":"ৱচনং","h":" ","s":{"eng":"NULL"},"o":{}},{"w":"সৎৱর","h":"-","s":{"eng":"NULL"},"o":{}},{"w":"রচনং","h":"","s":{"eng":"NULL"},"o":{}}],
      [{"w":"পূরয়","h":" ","s":{"eng":"NULL"},"o":{}},{"w":"মধুরিপুকামম্","h":" ॥৭॥","s":{"eng":"NULL"},"o":{}}]],
    "translation":{"eng":"UNDEFINED"}},{
    "lines":[
      [{"w":"শ্রীজয়দেৱে","h":" ","s":{"eng":"NULL"},"o":{}},{"w":"কৃত","h":"-","s":{"eng":"NULL"},"o":{}},{"w":"হরি","h":"-","s":{"eng":"NULL"},"o":{}},{"w":"সেৱে","h":"","s":{"eng":"NULL"},"o":{}}],
      [{"w":"ভণতি","h":" ","s":{"eng":"NULL"},"o":{}},{"w":"পরমরমণীযম্","h":" ।","s":{"eng":"NULL"},"o":{}}],
      [{"w":"প্রমুদিত","h":"-","s":{"eng":"NULL"},"o":{}},{"w":"হৃদয়ং","h":" ","s":{"eng":"NULL"},"o":{}},{"w":"হরিমতি","h":"-","s":{"eng":"NULL"},"o":{}},{"w":"সদয়ং","h":"","s":{"eng":"NULL"},"o":{}}],
      [{"w":"নমত","h":" ","s":{"eng":"NULL"},"o":{}},{"w":"সুকৃত","h":"-","s":{"eng":"NULL"},"o":{}},{"w":"কমনীয়ম্","h":" ॥৮॥","s":{"eng":"NULL"},"o":{}}]],
    "translation":{"eng":"UNDEFINED"}},{
    "lines":[
      []]}
  ]
}