{
  "uid":"K44",
  "title":"জীবে কৃপা করি’, গোলোকের হরি",
  "author":"bt",
  "language":"ben",
  "notes":[],
  "audio":[],
  "has_synonyms":false,
  "has_translations":false,
  "legend":{"w":"word","h":"hint","s":"synonym","o":"override"},
  "verses":[{
    "lines":[
      [{"w":"জীবে","h":" ","s":{"eng":"NULL"},"o":{}},{"w":"কৃপা","h":" ","s":{"eng":"NULL"},"o":{}},{"w":"করি’","h":",    ","s":{"eng":"NULL"},"o":{}},{"w":"গোলোকের","h":" ","s":{"eng":"NULL"},"o":{}},{"w":"হরি","h":",","s":{"eng":"NULL"},"o":{}}],
      [{"w":"ব্রজভাব","h":" ","s":{"eng":"NULL"},"o":{}},{"w":"প্রকাশিল","h":" ।","s":{"eng":"NULL"},"o":{}}],
      [{"w":"সে","h":" ","s":{"eng":"NULL"},"o":{}},{"w":"ভাব","h":"-","s":{"eng":"NULL"},"o":{}},{"w":"রসজ্ঞ","h":",    ","s":{"eng":"NULL"},"o":{}},{"w":"বৃন্দাবনযোগ্য","h":",","s":{"eng":"NULL"},"o":{}}],
      [{"w":"জড়বুদ্ধি","h":" ","s":{"eng":"NULL"},"o":{}},{"w":"না","h":" ","s":{"eng":"NULL"},"o":{}},{"w":"হইল","h":" ॥১॥","s":{"eng":"NULL"},"o":{}}]],
    "translation":{"eng":"UNDEFINED"}},{
    "lines":[
      [{"w":"কৃষ্ণলীলা","h":"-","s":{"eng":"NULL"},"o":{}},{"w":"সমুদ্র","h":" ","s":{"eng":"NULL"},"o":{}},{"w":"অপার","h":" ।","s":{"eng":"NULL"},"o":{}}],
      [{"w":"বৈকুণ্ঠ","h":"-","s":{"eng":"NULL"},"o":{}},{"w":"বিহার","h":",    ","s":{"eng":"NULL"},"o":{}},{"w":"সমান","h":" ","s":{"eng":"NULL"},"o":{}},{"w":"ইঁহার","h":",","s":{"eng":"NULL"},"o":{}}],
      [{"w":"কভু","h":" ","s":{"eng":"NULL"},"o":{}},{"w":"নহে","h":" ","s":{"eng":"NULL"},"o":{}},{"w":"জান’","h":" ","s":{"eng":"NULL"},"o":{}},{"w":"সার","h":" ॥২॥","s":{"eng":"NULL"},"o":{}}]],
    "translation":{"eng":"UNDEFINED"}},{
    "lines":[
      [{"w":"কৃষ্ণ","h":"-","s":{"eng":"NULL"},"o":{}},{"w":"নরাকার","h":",    ","s":{"eng":"NULL"},"o":{}},{"w":"সর্ব্ব","h":"-","s":{"eng":"NULL"},"o":{}},{"w":"রসাধার","h":",","s":{"eng":"NULL"},"o":{}}],
      [{"w":"শৃঙ্গারের","h":" ","s":{"eng":"NULL"},"o":{}},{"w":"বিশেষতঃ","h":" ।","s":{"eng":"NULL"},"o":{}}],
      [{"w":"বৈকুণ্ঠ","h":"-","s":{"eng":"NULL"},"o":{}},{"w":"সাধক","h":",    ","s":{"eng":"NULL"},"o":{}},{"w":"সখ্যে","h":" ","s":{"eng":"NULL"},"o":{}},{"w":"অপারক","h":",","s":{"eng":"NULL"},"o":{}}],
      [{"w":"মধুরে","h":" ","s":{"eng":"NULL"},"o":{}},{"w":"না","h":" ","s":{"eng":"NULL"},"o":{}},{"w":"হয়","h":" ","s":{"eng":"NULL"},"o":{}},{"w":"রত","h":" ॥৩॥","s":{"eng":"NULL"},"o":{}}]],
    "translation":{"eng":"UNDEFINED"}},{
    "lines":[
      [{"w":"ব্রজে","h":" ","s":{"eng":"NULL"},"o":{}},{"w":"কৃষ্ণধন","h":",    ","s":{"eng":"NULL"},"o":{}},{"w":"নবীন","h":"-","s":{"eng":"NULL"},"o":{}},{"w":"মদন","h":",","s":{"eng":"NULL"},"o":{}}],
      [{"w":"অপ্রাকৃত","h":" ","s":{"eng":"NULL"},"o":{}},{"w":"রসময়","h":" ।","s":{"eng":"NULL"},"o":{}}],
      [{"w":"জীবের","h":" ","s":{"eng":"NULL"},"o":{}},{"w":"সহিত","h":",    ","s":{"eng":"NULL"},"o":{}},{"w":"নিত্য","h":"-","s":{"eng":"NULL"},"o":{}},{"w":"লীলোচিত","h":",","s":{"eng":"NULL"},"o":{}}],
      [{"w":"কৃষ্ণ","h":"-","s":{"eng":"NULL"},"o":{}},{"w":"গুণগণ","h":" ","s":{"eng":"NULL"},"o":{}},{"w":"হয়","h":" ॥৪॥","s":{"eng":"NULL"},"o":{}}]],
    "translation":{"eng":"UNDEFINED"}}
  ]
}