{
  "uid":"K47",
  "title":"মোর প্রভু মদনগোপাল গোবিন্দ গোপীনাথ",
  "author":"ndt",
  "language":"ben",
  "notes":["শ্রীকৃষ্ণ বিজ্ঞপ্তি","শব্দার্থঃ- আগুগুরি—অগ্রসর হইয়া; ভণে—জ্ঞাপন করে ।"],
  "audio":[],
  "has_synonyms":false,
  "has_translations":false,
  "legend":{"w":"word","h":"hint","s":"synonym","o":"override"},
  "verses":[{
    "lines":[
      [{"w":"মোর","h":" ","s":{"eng":"NULL"},"o":{}},{"w":"প্রভু","h":" ","s":{"eng":"NULL"},"o":{}},{"w":"মদনগোপাল","h":",    ","s":{"eng":"NULL"},"o":{}},{"w":"গোবিন্দ","h":" ","s":{"eng":"NULL"},"o":{}},{"w":"গোপীনাথ","h":",","s":{"eng":"NULL"},"o":{}}],
      [{"w":"দয়া","h":" ","s":{"eng":"NULL"},"o":{}},{"w":"কর","h":" ","s":{"eng":"NULL"},"o":{}},{"w":"মুঞি","h":" ","s":{"eng":"NULL"},"o":{}},{"w":"অধমেরে","h":" ।","s":{"eng":"NULL"},"o":{}}],
      [{"w":"সংসার","h":"-","s":{"eng":"NULL"},"o":{}},{"w":"সাগর","h":"-","s":{"eng":"NULL"},"o":{}},{"w":"মাঝে","h":",    ","s":{"eng":"NULL"},"o":{}},{"w":"পড়িয়া","h":" ","s":{"eng":"NULL"},"o":{}},{"w":"বৈয়াছি","h":" ","s":{"eng":"NULL"},"o":{}},{"w":"নাথ","h":",","s":{"eng":"NULL"},"o":{}}],
      [{"w":"কৃপাডোরে","h":" ","s":{"eng":"NULL"},"o":{}},{"w":"বান্ধি","h":" ","s":{"eng":"NULL"},"o":{}},{"w":"লহ","h":" ","s":{"eng":"NULL"},"o":{}},{"w":"মোরে","h":" ॥১॥","s":{"eng":"NULL"},"o":{}}]],
    "translation":{"eng":"UNDEFINED"}},{
    "lines":[
      [{"w":"অধম","h":" ","s":{"eng":"NULL"},"o":{}},{"w":"চণ্ডাল","h":" ","s":{"eng":"NULL"},"o":{}},{"w":"আমি","h":",    ","s":{"eng":"NULL"},"o":{}},{"w":"দয়ার","h":" ","s":{"eng":"NULL"},"o":{}},{"w":"ঠাকুর","h":" ","s":{"eng":"NULL"},"o":{}},{"w":"তুমি","h":",","s":{"eng":"NULL"},"o":{}}],
      [{"w":"শুনিয়াছি","h":" ","s":{"eng":"NULL"},"o":{}},{"w":"বৈষ্ণবের","h":" ","s":{"eng":"NULL"},"o":{}},{"w":"মুখে","h":" ।","s":{"eng":"NULL"},"o":{}}],
      [{"w":"এ","h":" ","s":{"eng":"NULL"},"o":{}},{"w":"বড়","h":" ","s":{"eng":"NULL"},"o":{}},{"w":"ভরসা","h":" ","s":{"eng":"NULL"},"o":{}},{"w":"মনে","h":",    ","s":{"eng":"NULL"},"o":{}},{"w":"লৈয়া","h":" ","s":{"eng":"NULL"},"o":{}},{"w":"ফেল","h":" ","s":{"eng":"NULL"},"o":{}},{"w":"বৃন্দাবনে","h":",","s":{"eng":"NULL"},"o":{}}],
      [{"w":"বংশীবট","h":" ","s":{"eng":"NULL"},"o":{}},{"w":"যেন","h":" ","s":{"eng":"NULL"},"o":{}},{"w":"দেখি","h":" ","s":{"eng":"NULL"},"o":{}},{"w":"সুখে","h":" ॥২॥","s":{"eng":"NULL"},"o":{}}]],
    "translation":{"eng":"UNDEFINED"}},{
    "lines":[
      [{"w":"কৃপা","h":" ","s":{"eng":"NULL"},"o":{}},{"w":"কর","h":" ","s":{"eng":"NULL"},"o":{}},{"w":"আগুগুরি’","h":",    ","s":{"eng":"NULL"},"o":{}},{"w":"লহ","h":" ","s":{"eng":"NULL"},"o":{}},{"w":"মোরে","h":" ","s":{"eng":"NULL"},"o":{}},{"w":"কেশে","h":" ","s":{"eng":"NULL"},"o":{}},{"w":"ধরি’","h":",","s":{"eng":"NULL"},"o":{}}],
      [{"w":"শ্রীযমুনা","h":" ","s":{"eng":"NULL"},"o":{}},{"w":"দেহ’","h":" ","s":{"eng":"NULL"},"o":{}},{"w":"পদছায়া","h":" ।","s":{"eng":"NULL"},"o":{}}],
      [{"w":"অনেক","h":" ","s":{"eng":"NULL"},"o":{}},{"w":"দিনের","h":" ","s":{"eng":"NULL"},"o":{}},{"w":"আশ","h":",    ","s":{"eng":"NULL"},"o":{}},{"w":"নহে","h":" ","s":{"eng":"NULL"},"o":{}},{"w":"যেন","h":" ","s":{"eng":"NULL"},"o":{}},{"w":"নৈরাশ","h":",","s":{"eng":"NULL"},"o":{}}],
      [{"w":"দয়া","h":" ","s":{"eng":"NULL"},"o":{}},{"w":"কর","h":", ","s":{"eng":"NULL"},"o":{}},{"w":"না","h":" ","s":{"eng":"NULL"},"o":{}},{"w":"করহ","h":" ","s":{"eng":"NULL"},"o":{}},{"w":"মায়া","h":" ॥৩॥","s":{"eng":"NULL"},"o":{}}]],
    "translation":{"eng":"UNDEFINED"}},{
    "lines":[
      [{"w":"অনিত্য","h":" ","s":{"eng":"NULL"},"o":{}},{"w":"এ","h":" ","s":{"eng":"NULL"},"o":{}},{"w":"দেহ","h":" ","s":{"eng":"NULL"},"o":{}},{"w":"ধরি’","h":",    ","s":{"eng":"NULL"},"o":{}},{"w":"আপন","h":" ","s":{"eng":"NULL"},"o":{}},{"w":"আপন","h":" ","s":{"eng":"NULL"},"o":{}},{"w":"করি’","h":",","s":{"eng":"NULL"},"o":{}}],
      [{"w":"পাছে","h":" ","s":{"eng":"NULL"},"o":{}},{"w":"পাছে","h":" ","s":{"eng":"NULL"},"o":{}},{"w":"শমনের","h":" ","s":{"eng":"NULL"},"o":{}},{"w":"ভয়","h":" ।","s":{"eng":"NULL"},"o":{}}],
      [{"w":"নরোত্তমদাস","h":" ","s":{"eng":"NULL"},"o":{}},{"w":"ভণে","h":",    ","s":{"eng":"NULL"},"o":{}},{"w":"প্রাণ","h":" ","s":{"eng":"NULL"},"o":{}},{"w":"কান্দে","h":" ","s":{"eng":"NULL"},"o":{}},{"w":"রাত্রিদিনে","h":",","s":{"eng":"NULL"},"o":{}}],
      [{"w":"পাছে","h":" ","s":{"eng":"NULL"},"o":{}},{"w":"ব্রজপ্রাপ্তি","h":" ","s":{"eng":"NULL"},"o":{}},{"w":"নাহি","h":" ","s":{"eng":"NULL"},"o":{}},{"w":"হয়","h":" ॥৪॥","s":{"eng":"NULL"},"o":{}}]],
    "translation":{"eng":"UNDEFINED"}}
  ]
}