{
  "uid":"MS55",
  "title":"ওরে মন! ভাবিয়া না বুঝ আপনাকে",
  "author":"pdt",
  "language":"ben",
  "notes":["(১৬)"],
  "audio":[],
  "has_synonyms":false,
  "has_translations":false,
  "legend":{"w":"word","h":"hint","s":"synonym","o":"override"},
  "verses":[{
    "lines":[
      [{"w":"ওরে","h":" ","s":{"eng":"NULL"},"o":{}},{"w":"মন","h":"!  ","s":{"eng":"NULL"},"o":{}},{"w":"ভাবিয়া","h":" ","s":{"eng":"NULL"},"o":{}},{"w":"না","h":" ","s":{"eng":"NULL"},"o":{}},{"w":"বুঝ","h":" ","s":{"eng":"NULL"},"o":{}},{"w":"আপনাকে","h":" ।","s":{"eng":"NULL"},"o":{}}],
      [{"w":"যা’র","h":" ","s":{"eng":"NULL"},"o":{}},{"w":"লাগি’","h":" ","s":{"eng":"NULL"},"o":{}},{"w":"দুঃখ","h":" ","s":{"eng":"NULL"},"o":{}},{"w":"কর","h":",    ","s":{"eng":"NULL"},"o":{}},{"w":"স্বদেশে","h":" ","s":{"eng":"NULL"},"o":{}},{"w":"বিদেশে","h":" ","s":{"eng":"NULL"},"o":{}},{"w":"ফির","h":",","s":{"eng":"NULL"},"o":{}}],
      [{"w":"সে","h":"-","s":{"eng":"NULL"},"o":{}},{"w":"জন","h":" ","s":{"eng":"NULL"},"o":{}},{"w":"কি","h":" ","s":{"eng":"NULL"},"o":{}},{"w":"সুখ","h":" ","s":{"eng":"NULL"},"o":{}},{"w":"দিবে","h":" ","s":{"eng":"NULL"},"o":{}},{"w":"তোকে","h":" ॥১॥","s":{"eng":"NULL"},"o":{}}]],
    "translation":{"eng":"UNDEFINED"}},{
    "lines":[
      [{"w":"যাবৎ","h":" ","s":{"eng":"NULL"},"o":{}},{"w":"সামর্থ্য","h":" ","s":{"eng":"NULL"},"o":{}},{"w":"আছে","h":",    ","s":{"eng":"NULL"},"o":{}},{"w":"তাবৎ","h":" ","s":{"eng":"NULL"},"o":{}},{"w":"তোমার","h":" ","s":{"eng":"NULL"},"o":{}},{"w":"কাছে","h":",","s":{"eng":"NULL"},"o":{}}],
      [{"w":"যাবৎ","h":" ","s":{"eng":"NULL"},"o":{}},{"w":"আনিয়া","h":" ","s":{"eng":"NULL"},"o":{}},{"w":"দেহ","h":" ","s":{"eng":"NULL"},"o":{}},{"w":"অর্থ","h":" ।","s":{"eng":"NULL"},"o":{}}],
      [{"w":"যখন","h":" ","s":{"eng":"NULL"},"o":{}},{"w":"সে","h":" ","s":{"eng":"NULL"},"o":{}},{"w":"গন্ধ","h":" ","s":{"eng":"NULL"},"o":{}},{"w":"নাই","h":",    ","s":{"eng":"NULL"},"o":{}},{"w":"ডাকিলে","h":" ","s":{"eng":"NULL"},"o":{}},{"w":"না","h":" ","s":{"eng":"NULL"},"o":{}},{"w":"শুনে","h":" ","s":{"eng":"NULL"},"o":{}},{"w":"ভাই","h":",","s":{"eng":"NULL"},"o":{}}],
      [{"w":"না","h":" ","s":{"eng":"NULL"},"o":{}},{"w":"পুছে","h":", ","s":{"eng":"NULL"},"o":{}},{"w":"দেখিলে","h":" ","s":{"eng":"NULL"},"o":{}},{"w":"অসমর্থ","h":" ॥২॥","s":{"eng":"NULL"},"o":{}}]],
    "translation":{"eng":"UNDEFINED"}},{
    "lines":[
      [{"w":"অবস্থা","h":" ","s":{"eng":"NULL"},"o":{}},{"w":"দেখিয়া","h":" ","s":{"eng":"NULL"},"o":{}},{"w":"হাসে","h":",    ","s":{"eng":"NULL"},"o":{}},{"w":"ভাল","h":" ","s":{"eng":"NULL"},"o":{}},{"w":"কথা","h":" ","s":{"eng":"NULL"},"o":{}},{"w":"মন্দ","h":" ","s":{"eng":"NULL"},"o":{}},{"w":"বাসে","h":",","s":{"eng":"NULL"},"o":{}}],
      [{"w":"বাঁকা","h":"-","s":{"eng":"NULL"},"o":{}},{"w":"মুখে","h":" ","s":{"eng":"NULL"},"o":{}},{"w":"ও","h":" ","s":{"eng":"NULL"},"o":{}},{"w":"নাক","h":"-","s":{"eng":"NULL"},"o":{}},{"w":"তোলাই","h":" ।","s":{"eng":"NULL"},"o":{}}],
      [{"w":"ক্ষুধায়","h":" ","s":{"eng":"NULL"},"o":{}},{"w":"না","h":" ","s":{"eng":"NULL"},"o":{}},{"w":"দেয়","h":" ","s":{"eng":"NULL"},"o":{}},{"w":"ভাত","h":",    ","s":{"eng":"NULL"},"o":{}},{"w":"তা’তে","h":" ","s":{"eng":"NULL"},"o":{}},{"w":"আর","h":" ","s":{"eng":"NULL"},"o":{}},{"w":"কটু","h":" ","s":{"eng":"NULL"},"o":{}},{"w":"বাত","h":",","s":{"eng":"NULL"},"o":{}}],
      [{"w":"কহে","h":" ","s":{"eng":"NULL"},"o":{}},{"w":"একি","h":" ","s":{"eng":"NULL"},"o":{}},{"w":"হইল","h":" ","s":{"eng":"NULL"},"o":{}},{"w":"বালাই","h":" ॥৩॥","s":{"eng":"NULL"},"o":{}}]],
    "translation":{"eng":"UNDEFINED"}},{
    "lines":[
      [{"w":"দিনে","h":" ","s":{"eng":"NULL"},"o":{}},{"w":"দিনে","h":" ","s":{"eng":"NULL"},"o":{}},{"w":"খাট","h":" ","s":{"eng":"NULL"},"o":{}},{"w":"রতি","h":",    ","s":{"eng":"NULL"},"o":{}},{"w":"কিসে","h":" ","s":{"eng":"NULL"},"o":{}},{"w":"আর","h":" ","s":{"eng":"NULL"},"o":{}},{"w":"পিতা","h":" ","s":{"eng":"NULL"},"o":{}},{"w":"পতি","h":",","s":{"eng":"NULL"},"o":{}}],
      [{"w":"পরিজনে","h":" ","s":{"eng":"NULL"},"o":{}},{"w":"না","h":" ","s":{"eng":"NULL"},"o":{}},{"w":"কর","h":" ","s":{"eng":"NULL"},"o":{}},{"w":"বড়াই","h":" ।","s":{"eng":"NULL"},"o":{}}],
      [{"w":"যেবা","h":" ","s":{"eng":"NULL"},"o":{}},{"w":"আগে","h":" ","s":{"eng":"NULL"},"o":{}},{"w":"যোড়","h":"-","s":{"eng":"NULL"},"o":{}},{"w":"হাতে","h":",    ","s":{"eng":"NULL"},"o":{}},{"w":"তা’রা","h":" ","s":{"eng":"NULL"},"o":{}},{"w":"শুনায়","h":" ","s":{"eng":"NULL"},"o":{}},{"w":"নির্ঘাতে","h":",","s":{"eng":"NULL"},"o":{}}],
      [{"w":"এ","h":" ","s":{"eng":"NULL"},"o":{}},{"w":"সময়ে","h":" ","s":{"eng":"NULL"},"o":{}},{"w":"বন্ধু","h":" ","s":{"eng":"NULL"},"o":{}},{"w":"কে","h":" ","s":{"eng":"NULL"},"o":{}},{"w":"রে","h":" ","s":{"eng":"NULL"},"o":{}},{"w":"ভাই","h":" ॥৪॥","s":{"eng":"NULL"},"o":{}}]],
    "translation":{"eng":"UNDEFINED"}},{
    "lines":[
      [{"w":"পরকে","h":" ","s":{"eng":"NULL"},"o":{}},{"w":"আপন","h":" ","s":{"eng":"NULL"},"o":{}},{"w":"করি","h":",    ","s":{"eng":"NULL"},"o":{}},{"w":"ভেবে","h":" ","s":{"eng":"NULL"},"o":{}},{"w":"মলি","h":" ","s":{"eng":"NULL"},"o":{}},{"w":"জন্ম","h":" ","s":{"eng":"NULL"},"o":{}},{"w":"ভরি","h":",","s":{"eng":"NULL"},"o":{}}],
      [{"w":"কে","h":" ","s":{"eng":"NULL"},"o":{}},{"w":"তুমি","h":", ","s":{"eng":"NULL"},"o":{}},{"w":"তোমার","h":" ","s":{"eng":"NULL"},"o":{}},{"w":"আছে","h":" ","s":{"eng":"NULL"},"o":{}},{"w":"কেবা","h":" ","s":{"eng":"NULL"},"o":{}},{"w":"?","h":"","s":{"eng":"NULL"},"o":{}}],
      [{"w":"প্রেমানন্দ","h":" ","s":{"eng":"NULL"},"o":{}},{"w":"কহে","h":" ","s":{"eng":"NULL"},"o":{}},{"w":"মতি","h":",    ","s":{"eng":"NULL"},"o":{}},{"w":"","h":"‘","s":{"eng":"NULL"},"o":{}},{"w":"কৃষ্ণ’","h":" ","s":{"eng":"NULL"},"o":{}},{"w":"বিনা","h":" ","s":{"eng":"NULL"},"o":{}},{"w":"নাহি","h":" ","s":{"eng":"NULL"},"o":{}},{"w":"গতি","h":",","s":{"eng":"NULL"},"o":{}}],
      [{"w":"কহ","h":" ","s":{"eng":"NULL"},"o":{}},{"w":"","h":"‘","s":{"eng":"NULL"},"o":{}},{"w":"কৃষ্ণ’","h":"—","s":{"eng":"NULL"},"o":{}},{"w":"এ","h":" ","s":{"eng":"NULL"},"o":{}},{"w":"দুঃখ","h":" ","s":{"eng":"NULL"},"o":{}},{"w":"তরিবা","h":" ॥৫॥","s":{"eng":"NULL"},"o":{}}]],
    "translation":{"eng":"UNDEFINED"}}
  ]
}