{
  "uid":"N9",
  "title":"অক্রোধ পরমানন্দ",
  "author":"ldt",
  "language":"ben",
  "notes":[],
  "audio":[
    {"uid":"tama-1","fn":"N9-tama-1.mp3","meta":{"artist":"Tamal Krsna das","src":"04 Pañca-tattva/[06] Akrodha Paramānanda/tama-akrodha_paramananda.mp3"}}],
  "has_synonyms":true,
  "has_translations":true,
  "legend":{"w":"word","h":"hint","s":"synonym","o":"override"},
  "verses":[{
    "lines":[
      [{"w":"অক্রোধ","h":" ","s":{"eng":"free from anger"},"o":{}},{"w":"পরমানন্দ","h":" ","s":{"eng":"supreme + bliss"},"o":{}},{"w":"নিত্যানন্দ","h":"-","s":{"eng":"Nityānanda Prabhu"},"o":{}},{"w":"রায়","h":" ।","s":{"eng":"noble"},"o":{}}],
      [{"w":"অভিমান","h":"-","s":{"eng":"false ego"},"o":{}},{"w":"শূন্য","h":" ","s":{"eng":"devoid"},"o":{}},{"w":"নিতাই","h":" ","s":{"eng":"Nitāi"},"o":{}},{"w":"নগরে","h":" ","s":{"eng":"throughout the town"},"o":{}},{"w":"বেড়ায়","h":" ॥১॥","s":{"eng":"wanders"},"o":{}}]],
    "translation":{"eng":"The noble Nityānanda Prabhu, the personification of supreme transcendental bliss, is never angry. Devoid of all false ego, He wanders throughout the town."}},{
    "lines":[
      [{"w":"অধম","h":" ","s":{"eng":"lowly"},"o":{}},{"w":"পতিত","h":" ","s":{"eng":"fallen"},"o":{}},{"w":"জীবের","h":" ","s":{"eng":"of souls"},"o":{}},{"w":"দ্বারে","h":" ","s":{"eng":"from door to door"},"o":{}},{"w":"দ্বারে","h":" ","s":{"eng":"⬅1"},"o":{}},{"w":"গিয়া","h":" ।","s":{"eng":"having gone"},"o":{}}],
      [{"w":"হরিনাম","h":"-","s":{"eng":"the hare kṛṣṇa mahā-mantra"},"o":{}},{"w":"মহামন্ত্র","h":" ","s":{"eng":"⬅1"},"o":{}},{"w":"দিচ্ছেন","h":" ","s":{"eng":"he is giving"},"o":{}},{"w":"বিলাইয়া","h":" ॥২॥","s":{"eng":"having distributed"},"o":{}}]],
    "translation":{"eng":"Going from door to door among the residences of lowly and fallen souls, He freely distributes the harināma mahā-mantra."}},{
    "lines":[
      [{"w":"যা’রে","h":" ","s":{"eng":"to whom"},"o":{}},{"w":"দেখে","h":" ","s":{"eng":"he sees"},"o":{}},{"w":"তা’রে","h":" ","s":{"eng":"to them"},"o":{}},{"w":"কহে","h":" ","s":{"eng":"he says"},"o":{}},{"w":"দন্তে","h":" ","s":{"eng":"in teeth"},"o":{}},{"w":"তৃণ","h":" ","s":{"eng":"straw"},"o":{}},{"w":"ধরি’","h":" ।","s":{"eng":"having held"},"o":{}}],
      [{"w":"","h":"‘","s":{"eng":"NULL"},"o":{}},{"w":"আমারে","h":" ","s":{"eng":"to me"},"o":{}},{"w":"কিনিয়া","h":" ","s":{"eng":"purtchase for yourself [lit. having purchased, take]"},"o":{}},{"w":"লহ","h":", ","s":{"eng":"⬅1"},"o":{}},{"w":"বল","h":" ","s":{"eng":"call out"},"o":{}},{"w":"গৌরহরি","h":" ॥৩॥’","s":{"eng":"Gaurahari."},"o":{}}],
      [{"w":"এত","h":" ","s":{"eng":"this"},"o":{}},{"w":"বলি’","h":" ","s":{"eng":"having spoken"},"o":{}},{"w":"নিত্যানন্দ","h":" ","s":{"eng":"Nityānanda"},"o":{}},{"w":"ভূমে","h":" ","s":{"eng":"on the ground"},"o":{}},{"w":"গড়ি’","h":" ","s":{"eng":"rolls"},"o":{}},{"w":"যায়","h":" ।","s":{"eng":"⬅1"},"o":{}}],
      [{"w":"সোনার","h":" ","s":{"eng":"golden"},"o":{}},{"w":"পর্ব্বত","h":" ","s":{"eng":"mountain"},"o":{}},{"w":"যেন","h":" ","s":{"eng":"just like"},"o":{}},{"w":"ধূলাতে","h":" ","s":{"eng":"in the dust"},"o":{}},{"w":"লোটায়","h":" ॥৪॥","s":{"eng":"tumbles"},"o":{}}]],
    "translation":{"eng":"Holding a straw in His teeth, He calls out to whomever He sees, “Please purchase Me by calling out ‘Gaurahari!’ ” Speaking in this way, Nityānanda Prabhu rolls on the ground, appearing like a golden mountain tumbling in the dust."}},{
    "lines":[
      [{"w":"হেন","h":" ","s":{"eng":"such"},"o":{}},{"w":"অবতারে","h":" ","s":{"eng":"for an avatār"},"o":{}},{"w":"যা’র","h":" ","s":{"eng":"whose"},"o":{}},{"w":"রতি","h":" ","s":{"eng":"attachment"},"o":{}},{"w":"না","h":" ","s":{"eng":"not janmilô"},"o":{}},{"w":"জন্মিল","h":" ।","s":{"eng":"NULL"},"o":{}}],
      [{"w":"লোচন","h":" ","s":{"eng":"Locana"},"o":{}},{"w":"বলে","h":" ","s":{"eng":"says"},"o":{}},{"w":"সেই","h":" ","s":{"eng":"that"},"o":{}},{"w":"পাপী","h":" ","s":{"eng":"sinner"},"o":{}},{"w":"এল","h":" ","s":{"eng":"came"},"o":{}},{"w":"আর","h":" ","s":{"eng":"and"},"o":{}},{"w":"গেল","h":" ॥৫॥","s":{"eng":"went"},"o":{}}]],
    "translation":{"eng":"Locana dāsa says, “That sinful person who has not experienced the awakening of attachment for such an avatāra simply comes and goes [in the endless cycle of birth and death].”"}}
  ]
}