{
  "uid":"UP2",
  "title":"সাধুসঙ্গ না হইল হায়!",
  "author":"bt",
  "language":"ben",
  "notes":[],
  "audio":[],
  "has_synonyms":false,
  "has_translations":false,
  "legend":{"w":"word","h":"hint","s":"synonym","o":"override"},
  "verses":[{
    "lines":[
      [{"w":"সাধুসঙ্গ","h":" ","s":{"eng":"NULL"},"o":{}},{"w":"না","h":" ","s":{"eng":"NULL"},"o":{}},{"w":"হইল","h":" ","s":{"eng":"NULL"},"o":{}},{"w":"হায়","h":"!","s":{"eng":"NULL"},"o":{}}],
      [{"w":"গেল","h":" ","s":{"eng":"NULL"},"o":{}},{"w":"দিন","h":" ","s":{"eng":"NULL"},"o":{}},{"w":"অকারণ","h":",    ","s":{"eng":"NULL"},"o":{}},{"w":"করি’","h":" ","s":{"eng":"NULL"},"o":{}},{"w":"অর্থ","h":" ","s":{"eng":"NULL"},"o":{}},{"w":"উপার্জ্জন","h":",","s":{"eng":"NULL"},"o":{}}],
      [{"w":"পরমার্থ","h":" ","s":{"eng":"NULL"},"o":{}},{"w":"রহিল","h":" ","s":{"eng":"NULL"},"o":{}},{"w":"কোথায়","h":" ॥১॥","s":{"eng":"NULL"},"o":{}}]],
    "translation":{"eng":"UNDEFINED"}},{
    "lines":[
      [{"w":"সুবর্ণ","h":" ","s":{"eng":"NULL"},"o":{}},{"w":"করিয়া","h":" ","s":{"eng":"NULL"},"o":{}},{"w":"ত্যাগ","h":",    ","s":{"eng":"NULL"},"o":{}},{"w":"তুচ্ছ","h":" ","s":{"eng":"NULL"},"o":{}},{"w":"লোষ্ট্রে","h":" ","s":{"eng":"NULL"},"o":{}},{"w":"অনুরাগ","h":",","s":{"eng":"NULL"},"o":{}}],
      [{"w":"দুর্ভাগার","h":" ","s":{"eng":"NULL"},"o":{}},{"w":"এই","h":" ","s":{"eng":"NULL"},"o":{}},{"w":"ত’","h":" ","s":{"eng":"NULL"},"o":{}},{"w":"লক্ষণ","h":" ।","s":{"eng":"NULL"},"o":{}}],
      [{"w":"কৃষ্ণেতর","h":" ","s":{"eng":"NULL"},"o":{}},{"w":"সঙ্গ","h":" ","s":{"eng":"NULL"},"o":{}},{"w":"করি’","h":",    ","s":{"eng":"NULL"},"o":{}},{"w":"সাধুজনে","h":" ","s":{"eng":"NULL"},"o":{}},{"w":"পরিহরি’","h":",","s":{"eng":"NULL"},"o":{}}],
      [{"w":"মদগর্ব্বে","h":" ","s":{"eng":"NULL"},"o":{}},{"w":"কাটা’নু","h":" ","s":{"eng":"NULL"},"o":{}},{"w":"জীবন","h":" ॥২॥","s":{"eng":"NULL"},"o":{}}]],
    "translation":{"eng":"UNDEFINED"}},{
    "lines":[
      [{"w":"ভক্তিমুদ্রা","h":"-","s":{"eng":"NULL"},"o":{}},{"w":"দরশনে","h":",    ","s":{"eng":"NULL"},"o":{}},{"w":"হাস্য","h":" ","s":{"eng":"NULL"},"o":{}},{"w":"করিতাম","h":" ","s":{"eng":"NULL"},"o":{}},{"w":"মনে","h":",","s":{"eng":"NULL"},"o":{}}],
      [{"w":"বাতুলতা","h":" ","s":{"eng":"NULL"},"o":{}},{"w":"বলিয়া","h":" ","s":{"eng":"NULL"},"o":{}},{"w":"তাহায়","h":" ।","s":{"eng":"NULL"},"o":{}}],
      [{"w":"যে","h":" ","s":{"eng":"NULL"},"o":{}},{"w":"সভ্যতা","h":" ","s":{"eng":"NULL"},"o":{}},{"w":"শ্রেষ্ঠ","h":" ","s":{"eng":"NULL"},"o":{}},{"w":"গণি’","h":",    ","s":{"eng":"NULL"},"o":{}},{"w":"হারাইনু","h":" ","s":{"eng":"NULL"},"o":{}},{"w":"চিন্তামণি","h":",","s":{"eng":"NULL"},"o":{}}],
      [{"w":"শেষে","h":" ","s":{"eng":"NULL"},"o":{}},{"w":"তাহা","h":" ","s":{"eng":"NULL"},"o":{}},{"w":"রহিল","h":" ","s":{"eng":"NULL"},"o":{}},{"w":"কোথায়","h":" ॥৩॥","s":{"eng":"NULL"},"o":{}}]],
    "translation":{"eng":"UNDEFINED"}},{
    "lines":[
      [{"w":"জ্ঞানের","h":" ","s":{"eng":"NULL"},"o":{}},{"w":"গরিমা","h":" ","s":{"eng":"NULL"},"o":{}},{"w":"বলে","h":",    ","s":{"eng":"NULL"},"o":{}},{"w":"ভক্তিরূপ","h":" ","s":{"eng":"NULL"},"o":{}},{"w":"সুসম্বলে","h":",","s":{"eng":"NULL"},"o":{}}],
      [{"w":"উপেক্ষিনু","h":" ","s":{"eng":"NULL"},"o":{}},{"w":"স্বার্থ","h":" ","s":{"eng":"NULL"},"o":{}},{"w":"পাশরিয়া","h":" ।","s":{"eng":"NULL"},"o":{}}],
      [{"w":"দুষ্ট","h":" ","s":{"eng":"NULL"},"o":{}},{"w":"জড়াশ্রিত","h":" ","s":{"eng":"NULL"},"o":{}},{"w":"জ্ঞান","h":",    ","s":{"eng":"NULL"},"o":{}},{"w":"এবে","h":" ","s":{"eng":"NULL"},"o":{}},{"w":"হ’ল","h":" ","s":{"eng":"NULL"},"o":{}},{"w":"অন্তর্দ্ধান","h":",","s":{"eng":"NULL"},"o":{}}],
      [{"w":"কর্ম্মভোগে","h":" ","s":{"eng":"NULL"},"o":{}},{"w":"আমাকে","h":" ","s":{"eng":"NULL"},"o":{}},{"w":"রাখিয়া","h":" ॥৪॥","s":{"eng":"NULL"},"o":{}}]],
    "translation":{"eng":"UNDEFINED"}},{
    "lines":[
      [{"w":"এবে","h":" ","s":{"eng":"NULL"},"o":{}},{"w":"যদি","h":" ","s":{"eng":"NULL"},"o":{}},{"w":"সাধুজনে","h":",    ","s":{"eng":"NULL"},"o":{}},{"w":"কৃপা","h":" ","s":{"eng":"NULL"},"o":{}},{"w":"করি’","h":" ","s":{"eng":"NULL"},"o":{}},{"w":"এ","h":" ","s":{"eng":"NULL"},"o":{}},{"w":"দুর্জ্জনে","h":",","s":{"eng":"NULL"},"o":{}}],
      [{"w":"দেন","h":" ","s":{"eng":"NULL"},"o":{}},{"w":"ভক্তি","h":"-","s":{"eng":"NULL"},"o":{}},{"w":"সমুদ্রের","h":" ","s":{"eng":"NULL"},"o":{}},{"w":"বিন্দু","h":" ।","s":{"eng":"NULL"},"o":{}}],
      [{"w":"তা’","h":" ","s":{"eng":"NULL"},"o":{}},{"w":"হইলে","h":" ","s":{"eng":"NULL"},"o":{}},{"w":"অনায়াসে","h":",    ","s":{"eng":"NULL"},"o":{}},{"w":"মুক্ত","h":" ","s":{"eng":"NULL"},"o":{}},{"w":"হ’য়ে","h":" ","s":{"eng":"NULL"},"o":{}},{"w":"ভবপাশে","h":",","s":{"eng":"NULL"},"o":{}}],
      [{"w":"পার","h":" ","s":{"eng":"NULL"},"o":{}},{"w":"হই","h":" ","s":{"eng":"NULL"},"o":{}},{"w":"এ","h":" ","s":{"eng":"NULL"},"o":{}},{"w":"সংসার","h":"-","s":{"eng":"NULL"},"o":{}},{"w":"সিন্ধু","h":" ॥৫॥","s":{"eng":"NULL"},"o":{}}]],
    "translation":{"eng":"UNDEFINED"}}
  ]
}